mlmilvus/__init__.py
mlmilvus/base.py
mlmilvus/cls_openai.py
mlmilvus/cls_st.py
mlmilvus/cls_tei.py
mlmilvus/__pycache__/__init__.cpython-312.pyc
mlmilvus/__pycache__/base.cpython-312.pyc
mlmilvus/__pycache__/cls_tei.cpython-312.pyc
mlmilvus-1.0.2.dist-info/METADATA
mlmilvus-1.0.2.dist-info/WHEEL
mlmilvus-1.0.2.dist-info/top_level.txt
mlmilvus-1.0.2.dist-info/RECORD
