Metadata-Version: 2.4
Name: mlmilvus
Version: 1.0.2
Summary: milvus数据库操作工具类
Home-page: https://www.python.org
Author: mengling
Author-email: 1321443305@qq.com
Requires-Python: >=3.8
Requires-Dist: pymilvus
Requires-Dist: torch
Dynamic: author
Dynamic: author-email
Dynamic: home-page
Dynamic: requires-dist
Dynamic: requires-python
Dynamic: summary
